logstash_pipeline_parser/__init__.py
logstash_pipeline_parser/pipeline.py
logstash_pipeline_parser/tree.py
logstash_pipeline_parser-0.0.2.dist-info/LICENSE
logstash_pipeline_parser-0.0.2.dist-info/METADATA
logstash_pipeline_parser-0.0.2.dist-info/WHEEL
logstash_pipeline_parser-0.0.2.dist-info/top_level.txt
logstash_pipeline_parser-0.0.2.dist-info/RECORD
